setup.py
contactware/__init__.py
contactware/admin.py
contactware/apps.py
contactware/defaults.py
contactware/forms.py
contactware/models.py
contactware/signals.py
contactware/urls.py
contactware/utils.py
contactware/views.py
contactware/__pycache__/__init__.cpython-35.pyc
contactware/__pycache__/apps.cpython-35.pyc
contactware/__pycache__/models.cpython-35.pyc
contactware/management/__init__.py
contactware/management/commands/__init__.py
contactware/management/commands/cleancontacts.py
contactware/migrations/0001_initial.py
contactware/migrations/0002_contactmessage_identifier.py
contactware/migrations/__init__.py
contactware/tests/__init__.py
contactware/tests/tests_contacts.py
contactware/tests/testsettings.py
contactware/tests/__pycache__/__init__.cpython-35.pyc
contactware/tests/__pycache__/testsettings.cpython-35.pyc
django_contactware.egg-info/PKG-INFO
django_contactware.egg-info/SOURCES.txt
django_contactware.egg-info/dependency_links.txt
django_contactware.egg-info/top_level.txt